moveread/export/__init__.py
moveread/export/__init__.pyi
moveread/export/core.py
moveread/export/games.py
moveread/export/images.py
moveread/export/players.py
moveread/export/sheets.py
moveread/export/tensorflow.py
moveread_export-0.1.4.dist-info/METADATA
moveread_export-0.1.4.dist-info/WHEEL
moveread_export-0.1.4.dist-info/top_level.txt
moveread_export-0.1.4.dist-info/RECORD
